river_route/_Muskingum.py
river_route/__init__.py
river_route/__metadata__.py
river_route/_cli.py
river_route/metrics.py
river_route/runoff.py
river_route/tools.py
river_route-1.3.0.dist-info/licenses/LICENSE.txt
river_route-1.3.0.dist-info/METADATA
river_route-1.3.0.dist-info/WHEEL
river_route-1.3.0.dist-info/entry_points.txt
river_route-1.3.0.dist-info/top_level.txt
river_route-1.3.0.dist-info/RECORD
